pystardict.py
PyStarDict-0.8.data/data/share/pystardict/demo.py
PyStarDict-0.8.data/data/share/pystardict/profile_demo.py
PyStarDict-0.8.data/data/share/pystardict/stardict-quick_eng-rus-2.4.2/demo.py
PyStarDict-0.8.data/data/share/pystardict/stardict-quick_eng-rus-2.4.2/quick_english-russian.dict
PyStarDict-0.8.data/data/share/pystardict/stardict-quick_eng-rus-2.4.2/quick_english-russian.idx
PyStarDict-0.8.data/data/share/pystardict/stardict-quick_eng-rus-2.4.2/quick_english-russian.idx.oft
PyStarDict-0.8.data/data/share/pystardict/stardict-quick_eng-rus-2.4.2/quick_english-russian.ifo
PyStarDict-0.8.data/data/share/pystardict/stardict-quick_rus-eng-2.4.2/quick_russian-english.dict.dz
PyStarDict-0.8.data/data/share/pystardict/stardict-quick_rus-eng-2.4.2/quick_russian-english.idx
PyStarDict-0.8.data/data/share/pystardict/stardict-quick_rus-eng-2.4.2/quick_russian-english.idx.oft
PyStarDict-0.8.data/data/share/pystardict/stardict-quick_rus-eng-2.4.2/quick_russian-english.ifo
PyStarDict-0.8.dist-info/DESCRIPTION.rst
PyStarDict-0.8.dist-info/METADATA
PyStarDict-0.8.dist-info/RECORD
PyStarDict-0.8.dist-info/WHEEL
PyStarDict-0.8.dist-info/metadata.json
PyStarDict-0.8.dist-info/top_level.txt
