Metadata-Version: 2.0
Name: PyStarDict
Version: 0.8
Summary: Library for manipulating StarDict dictionaries from within Python
Home-page: http://www.ohloh.net/p/pystardict
Author: Serge Matveenko
Author-email: s@matveenko.ru
License: UNKNOWN
Platform: UNKNOWN
Requires-Dist: six
